[{"created_at": "Sat Dec 18 12:20:03 +0000 2021", "id": 1472179851792584704, "id_str": "1472179851792584704", "full_text": "@Jwahrheit 人生で初めて買ったCD「愛のうた」だった。\n幼少から既にその素質があったのか……。", "truncated": false, "display_text_range": [11, 52], "entities": {"hashtags": [], "symbols": [], "user_mentions": [{"screen_name": "Jwahrheit", "name": "JB", "id": 158962824, "id_str": "158962824", "indices": [0, 10]}], "urls": []}, "source": "<a href=\"http://twitter.com/download/iphone\" rel=\"nofollow\">Twitter for iPhone</a>", "in_reply_to_status_id": 1472161773638004740, "in_reply_to_status_id_str": "1472161773638004740", "in_reply_to_user_id": 158962824, "in_reply_to_user_id_str": "158962824", "in_reply_to_screen_name": "Jwahrheit", "user": {"id": 2429249618, "id_str": "2429249618", "name": "こはく総書記", "screen_name": "589pr", "location": "銀座で握手", "description": "生年不詳。テネシー州ジャクソン出身。小説家、連勤術師。コロナ禍に揺れる令和初頭の日本を風刺した二部作「Goodwill, いい感じ」「Good bey, Evangelion」で講談社メフィスト賞を受賞。後年は連勤術に没頭し、「40連勤による人体錬成術」と題した論文を発表。経団連から注目を浴びる。", "url": "https://t.co/dFT4P2Uhf2", "entities": {"url": {"urls": [{"url": "https://t.co/dFT4P2Uhf2", "expanded_url": "https://linktr.ee/589pr", "display_url": "linktr.ee/589pr", "indices": [0, 23]}]}, "description": {"urls": []}}, "protected": false, "followers_count": 25904, "friends_count": 371, "listed_count": 138, "created_at": "Sat Apr 05 17:48:55 +0000 2014", "favourites_count": 115809, "utc_offset": null, "time_zone": null, "geo_enabled": false, "verified": false, "statuses_count": 2863, "lang": null, "contributors_enabled": false, "is_translator": false, "is_translation_enabled": false, "profile_background_color": "022330", "profile_background_image_url": "http://abs.twimg.com/images/themes/theme14/bg.gif", "profile_background_image_url_https": "https://abs.twimg.com/images/themes/theme14/bg.gif", "profile_background_tile": true, "profile_image_url": "http://pbs.twimg.com/profile_images/1388337569360793601/DFxlOEhu_normal.jpg", "profile_image_url_https": "https://pbs.twimg.com/profile_images/1388337569360793601/DFxlOEhu_normal.jpg", "profile_banner_url": "https://pbs.twimg.com/profile_banners/2429249618/1609752962", "profile_link_color": "0084B4", "profile_sidebar_border_color": "000000", "profile_sidebar_fill_color": "000000", "profile_text_color": "000000", "profile_use_background_image": true, "has_extended_profile": true, "default_profile": false, "default_profile_image": false, "following": null, "follow_request_sent": null, "notifications": null, "translator_type": "none", "withheld_in_countries": []}, "geo": null, "coordinates": null, "place": null, "contributors": null, "is_quote_status": false, "retweet_count": 0, "favorite_count": 3, "favorited": false, "retweeted": false, "lang": "ja"}, {"created_at": "Sat Dec 18 07:29:53 +0000 2021", "id": 1472106829786513409, "id_str": "1472106829786513409", "full_text": "僕はピクミン！", "truncated": false, "display_text_range": [0, 7], "entities": {"hashtags": [], "symbols": [], "user_mentions": [], "urls": []}, "source": "<a href=\"http://twitter.com/download/iphone\" rel=\"nofollow\">Twitter for iPhone</a>", "in_reply_to_status_id": null, "in_reply_to_status_id_str": null, "in_reply_to_user_id": null, "in_reply_to_user_id_str": null, "in_reply_to_screen_name": null, "user": {"id": 2429249618, "id_str": "2429249618", "name": "こはく総書記", "screen_name": "589pr", "location": "銀座で握手", "description": "生年不詳。テネシー州ジャクソン出身。小説家、連勤術師。コロナ禍に揺れる令和初頭の日本を風刺した二部作「Goodwill, いい感じ」「Good bey, Evangelion」で講談社メフィスト賞を受賞。後年は連勤術に没頭し、「40連勤による人体錬成術」と題した論文を発表。経団連から注目を浴びる。", "url": "https://t.co/dFT4P2Uhf2", "entities": {"url": {"urls": [{"url": "https://t.co/dFT4P2Uhf2", "expanded_url": "https://linktr.ee/589pr", "display_url": "linktr.ee/589pr", "indices": [0, 23]}]}, "description": {"urls": []}}, "protected": false, "followers_count": 25904, "friends_count": 371, "listed_count": 138, "created_at": "Sat Apr 05 17:48:55 +0000 2014", "favourites_count": 115809, "utc_offset": null, "time_zone": null, "geo_enabled": false, "verified": false, "statuses_count": 2863, "lang": null, "contributors_enabled": false, "is_translator": false, "is_translation_enabled": false, "profile_background_color": "022330", "profile_background_image_url": "http://abs.twimg.com/images/themes/theme14/bg.gif", "profile_background_image_url_https": "https://abs.twimg.com/images/themes/theme14/bg.gif", "profile_background_tile": true, "profile_image_url": "http://pbs.twimg.com/profile_images/1388337569360793601/DFxlOEhu_normal.jpg", "profile_image_url_https": "https://pbs.twimg.com/profile_images/1388337569360793601/DFxlOEhu_normal.jpg", "profile_banner_url": "https://pbs.twimg.com/profile_banners/2429249618/1609752962", "profile_link_color": "0084B4", "profile_sidebar_border_color": "000000", "profile_sidebar_fill_color": "000000", "profile_text_color": "000000", "profile_use_background_image": true, "has_extended_profile": true, "default_profile": false, "default_profile_image": false, "following": null, "follow_request_sent": null, "notifications": null, "translator_type": "none", "withheld_in_countries": []}, "geo": null, "coordinates": null, "place": null, "contributors": null, "is_quote_status": false, "retweet_count": 1, "favorite_count": 45, "favorited": false, "retweeted": false, "lang": "ja"}, {"created_at": "Fri Dec 17 17:52:51 +0000 2021", "id": 1471901217475670016, "id_str": "1471901217475670016", "full_text": "終わらないのだ", "truncated": false, "display_text_range": [0, 7], "entities": {"hashtags": [], "symbols": [], "user_mentions": [], "urls": []}, "source": "<a href=\"http://twitter.com/download/iphone\" rel=\"nofollow\">Twitter for iPhone</a>", "in_reply_to_status_id": null, "in_reply_to_status_id_str": null, "in_reply_to_user_id": null, "in_reply_to_user_id_str": null, "in_reply_to_screen_name": null, "user": {"id": 2429249618, "id_str": "2429249618", "name": "こはく総書記", "screen_name": "589pr", "location": "銀座で握手", "description": "生年不詳。テネシー州ジャクソン出身。小説家、連勤術師。コロナ禍に揺れる令和初頭の日本を風刺した二部作「Goodwill, いい感じ」「Good bey, Evangelion」で講談社メフィスト賞を受賞。後年は連勤術に没頭し、「40連勤による人体錬成術」と題した論文を発表。経団連から注目を浴びる。", "url": "https://t.co/dFT4P2Uhf2", "entities": {"url": {"urls": [{"url": "https://t.co/dFT4P2Uhf2", "expanded_url": "https://linktr.ee/589pr", "display_url": "linktr.ee/589pr", "indices": [0, 23]}]}, "description": {"urls": []}}, "protected": false, "followers_count": 25904, "friends_count": 371, "listed_count": 138, "created_at": "Sat Apr 05 17:48:55 +0000 2014", "favourites_count": 115809, "utc_offset": null, "time_zone": null, "geo_enabled": false, "verified": false, "statuses_count": 2863, "lang": null, "contributors_enabled": false, "is_translator": false, "is_translation_enabled": false, "profile_background_color": "022330", "profile_background_image_url": "http://abs.twimg.com/images/themes/theme14/bg.gif", "profile_background_image_url_https": "https://abs.twimg.com/images/themes/theme14/bg.gif", "profile_background_tile": true, "profile_image_url": "http://pbs.twimg.com/profile_images/1388337569360793601/DFxlOEhu_normal.jpg", "profile_image_url_https": "https://pbs.twimg.com/profile_images/1388337569360793601/DFxlOEhu_normal.jpg", "profile_banner_url": "https://pbs.twimg.com/profile_banners/2429249618/1609752962", "profile_link_color": "0084B4", "profile_sidebar_border_color": "000000", "profile_sidebar_fill_color": "000000", "profile_text_color": "000000", "profile_use_background_image": true, "has_extended_profile": true, "default_profile": false, "default_profile_image": false, "following": null, "follow_request_sent": null, "notifications": null, "translator_type": "none", "withheld_in_countries": []}, "geo": null, "coordinates": null, "place": null, "contributors": null, "is_quote_status": false, "retweet_count": 0, "favorite_count": 39, "favorited": false, "retweeted": false, "lang": "ja"}, {"created_at": "Fri Dec 17 15:35:41 +0000 2021", "id": 1471866699020648450, "id_str": "1471866699020648450", "full_text": "@le10nov17 体現しちゃってるワケ", "truncated": false, "display_text_range": [11, 21], "entities": {"hashtags": [], "symbols": [], "user_mentions": [{"screen_name": "le10nov17", "name": "びっちめし@自転車,鋲,現況確認", "id": 928770430055227392, "id_str": "928770430055227392", "indices": [0, 10]}], "urls": []}, "source": "<a href=\"http://twitter.com/download/iphone\" rel=\"nofollow\">Twitter for iPhone</a>", "in_reply_to_status_id": 1471865754543091712, "in_reply_to_status_id_str": "1471865754543091712", "in_reply_to_user_id": 928770430055227392, "in_reply_to_user_id_str": "928770430055227392", "in_reply_to_screen_name": "le10nov17", "user": {"id": 2429249618, "id_str": "2429249618", "name": "こはく総書記", "screen_name": "589pr", "location": "銀座で握手", "description": "生年不詳。テネシー州ジャクソン出身。小説家、連勤術師。コロナ禍に揺れる令和初頭の日本を風刺した二部作「Goodwill, いい感じ」「Good bey, Evangelion」で講談社メフィスト賞を受賞。後年は連勤術に没頭し、「40連勤による人体錬成術」と題した論文を発表。経団連から注目を浴びる。", "url": "https://t.co/dFT4P2Uhf2", "entities": {"url": {"urls": [{"url": "https://t.co/dFT4P2Uhf2", "expanded_url": "https://linktr.ee/589pr", "display_url": "linktr.ee/589pr", "indices": [0, 23]}]}, "description": {"urls": []}}, "protected": false, "followers_count": 25904, "friends_count": 371, "listed_count": 138, "created_at": "Sat Apr 05 17:48:55 +0000 2014", "favourites_count": 115809, "utc_offset": null, "time_zone": null, "geo_enabled": false, "verified": false, "statuses_count": 2863, "lang": null, "contributors_enabled": false, "is_translator": false, "is_translation_enabled": false, "profile_background_color": "022330", "profile_background_image_url": "http://abs.twimg.com/images/themes/theme14/bg.gif", "profile_background_image_url_https": "https://abs.twimg.com/images/themes/theme14/bg.gif", "profile_background_tile": true, "profile_image_url": "http://pbs.twimg.com/profile_images/1388337569360793601/DFxlOEhu_normal.jpg", "profile_image_url_https": "https://pbs.twimg.com/profile_images/1388337569360793601/DFxlOEhu_normal.jpg", "profile_banner_url": "https://pbs.twimg.com/profile_banners/2429249618/1609752962", "profile_link_color": "0084B4", "profile_sidebar_border_color": "000000", "profile_sidebar_fill_color": "000000", "profile_text_color": "000000", "profile_use_background_image": true, "has_extended_profile": true, "default_profile": false, "default_profile_image": false, "following": null, "follow_request_sent": null, "notifications": null, "translator_type": "none", "withheld_in_countries": []}, "geo": null, "coordinates": null, "place": null, "contributors": null, "is_quote_status": false, "retweet_count": 0, "favorite_count": 0, "favorited": false, "retweeted": false, "lang": "ja"}, {"created_at": "Fri Dec 17 15:30:47 +0000 2021", "id": 1471865464204967937, "id_str": "1471865464204967937", "full_text": "気が付いたら華金終わってるじゃん……。", "truncated": false, "display_text_range": [0, 19], "entities": {"hashtags": [], "symbols": [], "user_mentions": [], "urls": []}, "source": "<a href=\"http://twitter.com/download/iphone\" rel=\"nofollow\">Twitter for iPhone</a>", "in_reply_to_status_id": null, "in_reply_to_status_id_str": null, "in_reply_to_user_id": null, "in_reply_to_user_id_str": null, "in_reply_to_screen_name": null, "user": {"id": 2429249618, "id_str": "2429249618", "name": "こはく総書記", "screen_name": "589pr", "location": "銀座で握手", "description": "生年不詳。テネシー州ジャクソン出身。小説家、連勤術師。コロナ禍に揺れる令和初頭の日本を風刺した二部作「Goodwill, いい感じ」「Good bey, Evangelion」で講談社メフィスト賞を受賞。後年は連勤術に没頭し、「40連勤による人体錬成術」と題した論文を発表。経団連から注目を浴びる。", "url": "https://t.co/dFT4P2Uhf2", "entities": {"url": {"urls": [{"url": "https://t.co/dFT4P2Uhf2", "expanded_url": "https://linktr.ee/589pr", "display_url": "linktr.ee/589pr", "indices": [0, 23]}]}, "description": {"urls": []}}, "protected": false, "followers_count": 25904, "friends_count": 371, "listed_count": 138, "created_at": "Sat Apr 05 17:48:55 +0000 2014", "favourites_count": 115809, "utc_offset": null, "time_zone": null, "geo_enabled": false, "verified": false, "statuses_count": 2863, "lang": null, "contributors_enabled": false, "is_translator": false, "is_translation_enabled": false, "profile_background_color": "022330", "profile_background_image_url": "http://abs.twimg.com/images/themes/theme14/bg.gif", "profile_background_image_url_https": "https://abs.twimg.com/images/themes/theme14/bg.gif", "profile_background_tile": true, "profile_image_url": "http://pbs.twimg.com/profile_images/1388337569360793601/DFxlOEhu_normal.jpg", "profile_image_url_https": "https://pbs.twimg.com/profile_images/1388337569360793601/DFxlOEhu_normal.jpg", "profile_banner_url": "https://pbs.twimg.com/profile_banners/2429249618/1609752962", "profile_link_color": "0084B4", "profile_sidebar_border_color": "000000", "profile_sidebar_fill_color": "000000", "profile_text_color": "000000", "profile_use_background_image": true, "has_extended_profile": true, "default_profile": false, "default_profile_image": false, "following": null, "follow_request_sent": null, "notifications": null, "translator_type": "none", "withheld_in_countries": []}, "geo": null, "coordinates": null, "place": null, "contributors": null, "is_quote_status": false, "retweet_count": 1, "favorite_count": 62, "favorited": false, "retweeted": false, "lang": "ja"}, {"created_at": "Thu Dec 16 10:14:08 +0000 2021", "id": 1471423391664345088, "id_str": "1471423391664345088", "full_text": "サウナは甘え、これからは自衛隊入隊で精神を整えろ。", "truncated": false, "display_text_range": [0, 25], "entities": {"hashtags": [], "symbols": [], "user_mentions": [], "urls": []}, "source": "<a href=\"http://twitter.com/download/iphone\" rel=\"nofollow\">Twitter for iPhone</a>", "in_reply_to_status_id": null, "in_reply_to_status_id_str": null, "in_reply_to_user_id": null, "in_reply_to_user_id_str": null, "in_reply_to_screen_name": null, "user": {"id": 2429249618, "id_str": "2429249618", "name": "こはく総書記", "screen_name": "589pr", "location": "銀座で握手", "description": "生年不詳。テネシー州ジャクソン出身。小説家、連勤術師。コロナ禍に揺れる令和初頭の日本を風刺した二部作「Goodwill, いい感じ」「Good bey, Evangelion」で講談社メフィスト賞を受賞。後年は連勤術に没頭し、「40連勤による人体錬成術」と題した論文を発表。経団連から注目を浴びる。", "url": "https://t.co/dFT4P2Uhf2", "entities": {"url": {"urls": [{"url": "https://t.co/dFT4P2Uhf2", "expanded_url": "https://linktr.ee/589pr", "display_url": "linktr.ee/589pr", "indices": [0, 23]}]}, "description": {"urls": []}}, "protected": false, "followers_count": 25904, "friends_count": 371, "listed_count": 138, "created_at": "Sat Apr 05 17:48:55 +0000 2014", "favourites_count": 115809, "utc_offset": null, "time_zone": null, "geo_enabled": false, "verified": false, "statuses_count": 2863, "lang": null, "contributors_enabled": false, "is_translator": false, "is_translation_enabled": false, "profile_background_color": "022330", "profile_background_image_url": "http://abs.twimg.com/images/themes/theme14/bg.gif", "profile_background_image_url_https": "https://abs.twimg.com/images/themes/theme14/bg.gif", "profile_background_tile": true, "profile_image_url": "http://pbs.twimg.com/profile_images/1388337569360793601/DFxlOEhu_normal.jpg", "profile_image_url_https": "https://pbs.twimg.com/profile_images/1388337569360793601/DFxlOEhu_normal.jpg", "profile_banner_url": "https://pbs.twimg.com/profile_banners/2429249618/1609752962", "profile_link_color": "0084B4", "profile_sidebar_border_color": "000000", "profile_sidebar_fill_color": "000000", "profile_text_color": "000000", "profile_use_background_image": true, "has_extended_profile": true, "default_profile": false, "default_profile_image": false, "following": null, "follow_request_sent": null, "notifications": null, "translator_type": "none", "withheld_in_countries": []}, "geo": null, "coordinates": null, "place": null, "contributors": null, "is_quote_status": false, "retweet_count": 4, "favorite_count": 91, "favorited": false, "retweeted": false, "lang": "ja"}, {"created_at": "Thu Dec 16 10:11:44 +0000 2021", "id": 1471422784006148098, "id_str": "1471422784006148098", "full_text": "投影されたスライドの組織力を高める施策「強い精神を作るために自衛隊入隊」が気になりすぎて他の話が何も入ってこなかった。", "truncated": false, "display_text_range": [0, 59], "entities": {"hashtags": [], "symbols": [], "user_mentions": [], "urls": []}, "source": "<a href=\"http://twitter.com/download/iphone\" rel=\"nofollow\">Twitter for iPhone</a>", "in_reply_to_status_id": null, "in_reply_to_status_id_str": null, "in_reply_to_user_id": null, "in_reply_to_user_id_str": null, "in_reply_to_screen_name": null, "user": {"id": 2429249618, "id_str": "2429249618", "name": "こはく総書記", "screen_name": "589pr", "location": "銀座で握手", "description": "生年不詳。テネシー州ジャクソン出身。小説家、連勤術師。コロナ禍に揺れる令和初頭の日本を風刺した二部作「Goodwill, いい感じ」「Good bey, Evangelion」で講談社メフィスト賞を受賞。後年は連勤術に没頭し、「40連勤による人体錬成術」と題した論文を発表。経団連から注目を浴びる。", "url": "https://t.co/dFT4P2Uhf2", "entities": {"url": {"urls": [{"url": "https://t.co/dFT4P2Uhf2", "expanded_url": "https://linktr.ee/589pr", "display_url": "linktr.ee/589pr", "indices": [0, 23]}]}, "description": {"urls": []}}, "protected": false, "followers_count": 25904, "friends_count": 371, "listed_count": 138, "created_at": "Sat Apr 05 17:48:55 +0000 2014", "favourites_count": 115809, "utc_offset": null, "time_zone": null, "geo_enabled": false, "verified": false, "statuses_count": 2863, "lang": null, "contributors_enabled": false, "is_translator": false, "is_translation_enabled": false, "profile_background_color": "022330", "profile_background_image_url": "http://abs.twimg.com/images/themes/theme14/bg.gif", "profile_background_image_url_https": "https://abs.twimg.com/images/themes/theme14/bg.gif", "profile_background_tile": true, "profile_image_url": "http://pbs.twimg.com/profile_images/1388337569360793601/DFxlOEhu_normal.jpg", "profile_image_url_https": "https://pbs.twimg.com/profile_images/1388337569360793601/DFxlOEhu_normal.jpg", "profile_banner_url": "https://pbs.twimg.com/profile_banners/2429249618/1609752962", "profile_link_color": "0084B4", "profile_sidebar_border_color": "000000", "profile_sidebar_fill_color": "000000", "profile_text_color": "000000", "profile_use_background_image": true, "has_extended_profile": true, "default_profile": false, "default_profile_image": false, "following": null, "follow_request_sent": null, "notifications": null, "translator_type": "none", "withheld_in_countries": []}, "geo": null, "coordinates": null, "place": null, "contributors": null, "is_quote_status": false, "retweet_count": 3, "favorite_count": 85, "favorited": false, "retweeted": false, "lang": "ja"}, {"created_at": "Thu Dec 16 03:39:31 +0000 2021", "id": 1471324082373558272, "id_str": "1471324082373558272", "full_text": "元気な親知らずを大学病院の口腔外科で一気に取りました。\n#querie_me \nhttps://t.co/LThNPM99L4", "truncated": false, "display_text_range": [0, 63], "entities": {"hashtags": [{"text": "querie_me", "indices": [28, 38]}], "symbols": [], "user_mentions": [], "urls": [{"url": "https://t.co/LThNPM99L4", "expanded_url": "https://querie.me/answer/0N6xvvvbmWENOCsHX7aN?timestamp=1639625969", "display_url": "querie.me/answer/0N6xvvv…", "indices": [40, 63]}]}, "source": "<a href=\"https://twitter.com/querie_me_app\" rel=\"nofollow\">querie.me</a>", "in_reply_to_status_id": null, "in_reply_to_status_id_str": null, "in_reply_to_user_id": null, "in_reply_to_user_id_str": null, "in_reply_to_screen_name": null, "user": {"id": 2429249618, "id_str": "2429249618", "name": "こはく総書記", "screen_name": "589pr", "location": "銀座で握手", "description": "生年不詳。テネシー州ジャクソン出身。小説家、連勤術師。コロナ禍に揺れる令和初頭の日本を風刺した二部作「Goodwill, いい感じ」「Good bey, Evangelion」で講談社メフィスト賞を受賞。後年は連勤術に没頭し、「40連勤による人体錬成術」と題した論文を発表。経団連から注目を浴びる。", "url": "https://t.co/dFT4P2Uhf2", "entities": {"url": {"urls": [{"url": "https://t.co/dFT4P2Uhf2", "expanded_url": "https://linktr.ee/589pr", "display_url": "linktr.ee/589pr", "indices": [0, 23]}]}, "description": {"urls": []}}, "protected": false, "followers_count": 25904, "friends_count": 371, "listed_count": 138, "created_at": "Sat Apr 05 17:48:55 +0000 2014", "favourites_count": 115809, "utc_offset": null, "time_zone": null, "geo_enabled": false, "verified": false, "statuses_count": 2863, "lang": null, "contributors_enabled": false, "is_translator": false, "is_translation_enabled": false, "profile_background_color": "022330", "profile_background_image_url": "http://abs.twimg.com/images/themes/theme14/bg.gif", "profile_background_image_url_https": "https://abs.twimg.com/images/themes/theme14/bg.gif", "profile_background_tile": true, "profile_image_url": "http://pbs.twimg.com/profile_images/1388337569360793601/DFxlOEhu_normal.jpg", "profile_image_url_https": "https://pbs.twimg.com/profile_images/1388337569360793601/DFxlOEhu_normal.jpg", "profile_banner_url": "https://pbs.twimg.com/profile_banners/2429249618/1609752962", "profile_link_color": "0084B4", "profile_sidebar_border_color": "000000", "profile_sidebar_fill_color": "000000", "profile_text_color": "000000", "profile_use_background_image": true, "has_extended_profile": true, "default_profile": false, "default_profile_image": false, "following": null, "follow_request_sent": null, "notifications": null, "translator_type": "none", "withheld_in_countries": []}, "geo": null, "coordinates": null, "place": null, "contributors": null, "is_quote_status": false, "retweet_count": 0, "favorite_count": 14, "favorited": false, "retweeted": false, "possibly_sensitive": false, "lang": "ja"}, {"created_at": "Thu Dec 16 03:30:09 +0000 2021", "id": 1471321722804908037, "id_str": "1471321722804908037", "full_text": "ボルゾイはお母さんの上で気持ちよさそうに寝てるけど、お母さんは40kgの重石を腹で受け止めるトレーニングに勤しむボディビルダーみたいな顔してる。 https://t.co/EqhcJUcLun", "truncated": false, "display_text_range": [0, 72], "entities": {"hashtags": [], "symbols": [], "user_mentions": [], "urls": [], "media": [{"id": 1471321718354448386, "id_str": "1471321718354448386", "indices": [73, 96], "media_url": "http://pbs.twimg.com/media/FGsvTrTVkAI_QSJ.jpg", "media_url_https": "https://pbs.twimg.com/media/FGsvTrTVkAI_QSJ.jpg", "url": "https://t.co/EqhcJUcLun", "display_url": "pic.twitter.com/EqhcJUcLun", "expanded_url": "https://twitter.com/589pr/status/1471321722804908037/photo/1", "type": "photo", "sizes": {"thumb": {"w": 150, "h": 150, "resize": "crop"}, "small": {"w": 680, "h": 510, "resize": "fit"}, "medium": {"w": 1200, "h": 900, "resize": "fit"}, "large": {"w": 1478, "h": 1108, "resize": "fit"}}}]}, "extended_entities": {"media": [{"id": 1471321718354448386, "id_str": "1471321718354448386", "indices": [73, 96], "media_url": "http://pbs.twimg.com/media/FGsvTrTVkAI_QSJ.jpg", "media_url_https": "https://pbs.twimg.com/media/FGsvTrTVkAI_QSJ.jpg", "url": "https://t.co/EqhcJUcLun", "display_url": "pic.twitter.com/EqhcJUcLun", "expanded_url": "https://twitter.com/589pr/status/1471321722804908037/photo/1", "type": "photo", "sizes": {"thumb": {"w": 150, "h": 150, "resize": "crop"}, "small": {"w": 680, "h": 510, "resize": "fit"}, "medium": {"w": 1200, "h": 900, "resize": "fit"}, "large": {"w": 1478, "h": 1108, "resize": "fit"}}}]}, "source": "<a href=\"http://twitter.com/download/iphone\" rel=\"nofollow\">Twitter for iPhone</a>", "in_reply_to_status_id": null, "in_reply_to_status_id_str": null, "in_reply_to_user_id": null, "in_reply_to_user_id_str": null, "in_reply_to_screen_name": null, "user": {"id": 2429249618, "id_str": "2429249618", "name": "こはく総書記", "screen_name": "589pr", "location": "銀座で握手", "description": "生年不詳。テネシー州ジャクソン出身。小説家、連勤術師。コロナ禍に揺れる令和初頭の日本を風刺した二部作「Goodwill, いい感じ」「Good bey, Evangelion」で講談社メフィスト賞を受賞。後年は連勤術に没頭し、「40連勤による人体錬成術」と題した論文を発表。経団連から注目を浴びる。", "url": "https://t.co/dFT4P2Uhf2", "entities": {"url": {"urls": [{"url": "https://t.co/dFT4P2Uhf2", "expanded_url": "https://linktr.ee/589pr", "display_url": "linktr.ee/589pr", "indices": [0, 23]}]}, "description": {"urls": []}}, "protected": false, "followers_count": 25904, "friends_count": 371, "listed_count": 138, "created_at": "Sat Apr 05 17:48:55 +0000 2014", "favourites_count": 115809, "utc_offset": null, "time_zone": null, "geo_enabled": false, "verified": false, "statuses_count": 2863, "lang": null, "contributors_enabled": false, "is_translator": false, "is_translation_enabled": false, "profile_background_color": "022330", "profile_background_image_url": "http://abs.twimg.com/images/themes/theme14/bg.gif", "profile_background_image_url_https": "https://abs.twimg.com/images/themes/theme14/bg.gif", "profile_background_tile": true, "profile_image_url": "http://pbs.twimg.com/profile_images/1388337569360793601/DFxlOEhu_normal.jpg", "profile_image_url_https": "https://pbs.twimg.com/profile_images/1388337569360793601/DFxlOEhu_normal.jpg", "profile_banner_url": "https://pbs.twimg.com/profile_banners/2429249618/1609752962", "profile_link_color": "0084B4", "profile_sidebar_border_color": "000000", "profile_sidebar_fill_color": "000000", "profile_text_color": "000000", "profile_use_background_image": true, "has_extended_profile": true, "default_profile": false, "default_profile_image": false, "following": null, "follow_request_sent": null, "notifications": null, "translator_type": "none", "withheld_in_countries": []}, "geo": null, "coordinates": null, "place": null, "contributors": null, "is_quote_status": false, "retweet_count": 9, "favorite_count": 216, "favorited": false, "retweeted": false, "possibly_sensitive": false, "lang": "ja"}, {"created_at": "Wed Dec 15 16:05:35 +0000 2021", "id": 1471149449116536834, "id_str": "1471149449116536834", "full_text": "逆に時差ない説", "truncated": false, "display_text_range": [0, 7], "entities": {"hashtags": [], "symbols": [], "user_mentions": [], "urls": []}, "source": "<a href=\"http://twitter.com/download/iphone\" rel=\"nofollow\">Twitter for iPhone</a>", "in_reply_to_status_id": null, "in_reply_to_status_id_str": null, "in_reply_to_user_id": null, "in_reply_to_user_id_str": null, "in_reply_to_screen_name": null, "user": {"id": 2429249618, "id_str": "2429249618", "name": "こはく総書記", "screen_name": "589pr", "location": "銀座で握手", "description": "生年不詳。テネシー州ジャクソン出身。小説家、連勤術師。コロナ禍に揺れる令和初頭の日本を風刺した二部作「Goodwill, いい感じ」「Good bey, Evangelion」で講談社メフィスト賞を受賞。後年は連勤術に没頭し、「40連勤による人体錬成術」と題した論文を発表。経団連から注目を浴びる。", "url": "https://t.co/dFT4P2Uhf2", "entities": {"url": {"urls": [{"url": "https://t.co/dFT4P2Uhf2", "expanded_url": "https://linktr.ee/589pr", "display_url": "linktr.ee/589pr", "indices": [0, 23]}]}, "description": {"urls": []}}, "protected": false, "followers_count": 25904, "friends_count": 371, "listed_count": 138, "created_at": "Sat Apr 05 17:48:55 +0000 2014", "favourites_count": 115809, "utc_offset": null, "time_zone": null, "geo_enabled": false, "verified": false, "statuses_count": 2863, "lang": null, "contributors_enabled": false, "is_translator": false, "is_translation_enabled": false, "profile_background_color": "022330", "profile_background_image_url": "http://abs.twimg.com/images/themes/theme14/bg.gif", "profile_background_image_url_https": "https://abs.twimg.com/images/themes/theme14/bg.gif", "profile_background_tile": true, "profile_image_url": "http://pbs.twimg.com/profile_images/1388337569360793601/DFxlOEhu_normal.jpg", "profile_image_url_https": "https://pbs.twimg.com/profile_images/1388337569360793601/DFxlOEhu_normal.jpg", "profile_banner_url": "https://pbs.twimg.com/profile_banners/2429249618/1609752962", "profile_link_color": "0084B4", "profile_sidebar_border_color": "000000", "profile_sidebar_fill_color": "000000", "profile_text_color": "000000", "profile_use_background_image": true, "has_extended_profile": true, "default_profile": false, "default_profile_image": false, "following": null, "follow_request_sent": null, "notifications": null, "translator_type": "none", "withheld_in_countries": []}, "geo": null, "coordinates": null, "place": null, "contributors": null, "is_quote_status": false, "retweet_count": 0, "favorite_count": 23, "favorited": false, "retweeted": false, "lang": "ja"}, {"created_at": "Wed Dec 15 16:05:18 +0000 2021", "id": 1471149374978011137, "id_str": "1471149374978011137", "full_text": "気が付いたら北米の終業から始業を見守ってしまった。", "truncated": false, "display_text_range": [0, 25], "entities": {"hashtags": [], "symbols": [], "user_mentions": [], "urls": []}, "source": "<a href=\"http://twitter.com/download/iphone\" rel=\"nofollow\">Twitter for iPhone</a>", "in_reply_to_status_id": null, "in_reply_to_status_id_str": null, "in_reply_to_user_id": null, "in_reply_to_user_id_str": null, "in_reply_to_screen_name": null, "user": {"id": 2429249618, "id_str": "2429249618", "name": "こはく総書記", "screen_name": "589pr", "location": "銀座で握手", "description": "生年不詳。テネシー州ジャクソン出身。小説家、連勤術師。コロナ禍に揺れる令和初頭の日本を風刺した二部作「Goodwill, いい感じ」「Good bey, Evangelion」で講談社メフィスト賞を受賞。後年は連勤術に没頭し、「40連勤による人体錬成術」と題した論文を発表。経団連から注目を浴びる。", "url": "https://t.co/dFT4P2Uhf2", "entities": {"url": {"urls": [{"url": "https://t.co/dFT4P2Uhf2", "expanded_url": "https://linktr.ee/589pr", "display_url": "linktr.ee/589pr", "indices": [0, 23]}]}, "description": {"urls": []}}, "protected": false, "followers_count": 25904, "friends_count": 371, "listed_count": 138, "created_at": "Sat Apr 05 17:48:55 +0000 2014", "favourites_count": 115809, "utc_offset": null, "time_zone": null, "geo_enabled": false, "verified": false, "statuses_count": 2863, "lang": null, "contributors_enabled": false, "is_translator": false, "is_translation_enabled": false, "profile_background_color": "022330", "profile_background_image_url": "http://abs.twimg.com/images/themes/theme14/bg.gif", "profile_background_image_url_https": "https://abs.twimg.com/images/themes/theme14/bg.gif", "profile_background_tile": true, "profile_image_url": "http://pbs.twimg.com/profile_images/1388337569360793601/DFxlOEhu_normal.jpg", "profile_image_url_https": "https://pbs.twimg.com/profile_images/1388337569360793601/DFxlOEhu_normal.jpg", "profile_banner_url": "https://pbs.twimg.com/profile_banners/2429249618/1609752962", "profile_link_color": "0084B4", "profile_sidebar_border_color": "000000", "profile_sidebar_fill_color": "000000", "profile_text_color": "000000", "profile_use_background_image": true, "has_extended_profile": true, "default_profile": false, "default_profile_image": false, "following": null, "follow_request_sent": null, "notifications": null, "translator_type": "none", "withheld_in_countries": []}, "geo": null, "coordinates": null, "place": null, "contributors": null, "is_quote_status": false, "retweet_count": 0, "favorite_count": 56, "favorited": false, "retweeted": false, "lang": "ja"}, {"created_at": "Wed Dec 15 03:48:07 +0000 2021", "id": 1470963858710081537, "id_str": "1470963858710081537", "full_text": "来期分の発注N億円\n#querie_me \nhttps://t.co/C0uk6GvUwX", "truncated": false, "display_text_range": [0, 45], "entities": {"hashtags": [{"text": "querie_me", "indices": [10, 20]}], "symbols": [], "user_mentions": [], "urls": [{"url": "https://t.co/C0uk6GvUwX", "expanded_url": "https://querie.me/answer/WSIzh5i69KgXCQBj3sNV?timestamp=1639540083", "display_url": "querie.me/answer/WSIzh5i…", "indices": [22, 45]}]}, "source": "<a href=\"https://twitter.com/querie_me_app\" rel=\"nofollow\">querie.me</a>", "in_reply_to_status_id": null, "in_reply_to_status_id_str": null, "in_reply_to_user_id": null, "in_reply_to_user_id_str": null, "in_reply_to_screen_name": null, "user": {"id": 2429249618, "id_str": "2429249618", "name": "こはく総書記", "screen_name": "589pr", "location": "銀座で握手", "description": "生年不詳。テネシー州ジャクソン出身。小説家、連勤術師。コロナ禍に揺れる令和初頭の日本を風刺した二部作「Goodwill, いい感じ」「Good bey, Evangelion」で講談社メフィスト賞を受賞。後年は連勤術に没頭し、「40連勤による人体錬成術」と題した論文を発表。経団連から注目を浴びる。", "url": "https://t.co/dFT4P2Uhf2", "entities": {"url": {"urls": [{"url": "https://t.co/dFT4P2Uhf2", "expanded_url": "https://linktr.ee/589pr", "display_url": "linktr.ee/589pr", "indices": [0, 23]}]}, "description": {"urls": []}}, "protected": false, "followers_count": 25904, "friends_count": 371, "listed_count": 138, "created_at": "Sat Apr 05 17:48:55 +0000 2014", "favourites_count": 115809, "utc_offset": null, "time_zone": null, "geo_enabled": false, "verified": false, "statuses_count": 2863, "lang": null, "contributors_enabled": false, "is_translator": false, "is_translation_enabled": false, "profile_background_color": "022330", "profile_background_image_url": "http://abs.twimg.com/images/themes/theme14/bg.gif", "profile_background_image_url_https": "https://abs.twimg.com/images/themes/theme14/bg.gif", "profile_background_tile": true, "profile_image_url": "http://pbs.twimg.com/profile_images/1388337569360793601/DFxlOEhu_normal.jpg", "profile_image_url_https": "https://pbs.twimg.com/profile_images/1388337569360793601/DFxlOEhu_normal.jpg", "profile_banner_url": "https://pbs.twimg.com/profile_banners/2429249618/1609752962", "profile_link_color": "0084B4", "profile_sidebar_border_color": "000000", "profile_sidebar_fill_color": "000000", "profile_text_color": "000000", "profile_use_background_image": true, "has_extended_profile": true, "default_profile": false, "default_profile_image": false, "following": null, "follow_request_sent": null, "notifications": null, "translator_type": "none", "withheld_in_countries": []}, "geo": null, "coordinates": null, "place": null, "contributors": null, "is_quote_status": false, "retweet_count": 0, "favorite_count": 19, "favorited": false, "retweeted": false, "possibly_sensitive": false, "lang": "ja"}, {"created_at": "Wed Dec 15 01:55:54 +0000 2021", "id": 1470935617408503808, "id_str": "1470935617408503808", "full_text": "交際費 目標達成 400% 了解", "truncated": false, "display_text_range": [0, 16], "entities": {"hashtags": [], "symbols": [], "user_mentions": [], "urls": []}, "source": "<a href=\"http://twitter.com/download/iphone\" rel=\"nofollow\">Twitter for iPhone</a>", "in_reply_to_status_id": null, "in_reply_to_status_id_str": null, "in_reply_to_user_id": null, "in_reply_to_user_id_str": null, "in_reply_to_screen_name": null, "user": {"id": 2429249618, "id_str": "2429249618", "name": "こはく総書記", "screen_name": "589pr", "location": "銀座で握手", "description": "生年不詳。テネシー州ジャクソン出身。小説家、連勤術師。コロナ禍に揺れる令和初頭の日本を風刺した二部作「Goodwill, いい感じ」「Good bey, Evangelion」で講談社メフィスト賞を受賞。後年は連勤術に没頭し、「40連勤による人体錬成術」と題した論文を発表。経団連から注目を浴びる。", "url": "https://t.co/dFT4P2Uhf2", "entities": {"url": {"urls": [{"url": "https://t.co/dFT4P2Uhf2", "expanded_url": "https://linktr.ee/589pr", "display_url": "linktr.ee/589pr", "indices": [0, 23]}]}, "description": {"urls": []}}, "protected": false, "followers_count": 25904, "friends_count": 371, "listed_count": 138, "created_at": "Sat Apr 05 17:48:55 +0000 2014", "favourites_count": 115809, "utc_offset": null, "time_zone": null, "geo_enabled": false, "verified": false, "statuses_count": 2863, "lang": null, "contributors_enabled": false, "is_translator": false, "is_translation_enabled": false, "profile_background_color": "022330", "profile_background_image_url": "http://abs.twimg.com/images/themes/theme14/bg.gif", "profile_background_image_url_https": "https://abs.twimg.com/images/themes/theme14/bg.gif", "profile_background_tile": true, "profile_image_url": "http://pbs.twimg.com/profile_images/1388337569360793601/DFxlOEhu_normal.jpg", "profile_image_url_https": "https://pbs.twimg.com/profile_images/1388337569360793601/DFxlOEhu_normal.jpg", "profile_banner_url": "https://pbs.twimg.com/profile_banners/2429249618/1609752962", "profile_link_color": "0084B4", "profile_sidebar_border_color": "000000", "profile_sidebar_fill_color": "000000", "profile_text_color": "000000", "profile_use_background_image": true, "has_extended_profile": true, "default_profile": false, "default_profile_image": false, "following": null, "follow_request_sent": null, "notifications": null, "translator_type": "none", "withheld_in_countries": []}, "geo": null, "coordinates": null, "place": null, "contributors": null, "is_quote_status": false, "retweet_count": 1, "favorite_count": 65, "favorited": false, "retweeted": false, "lang": "ja"}, {"created_at": "Tue Dec 14 16:13:56 +0000 2021", "id": 1470789160277807111, "id_str": "1470789160277807111", "full_text": "知らんアカがわざわざ名指しでツイートしているのを見付けて、反応して欲しいんだろうなぁと思いながらも静かに見守るタイプの優しさはありますよ。", "truncated": false, "display_text_range": [0, 69], "entities": {"hashtags": [], "symbols": [], "user_mentions": [], "urls": []}, "source": "<a href=\"http://twitter.com/download/iphone\" rel=\"nofollow\">Twitter for iPhone</a>", "in_reply_to_status_id": null, "in_reply_to_status_id_str": null, "in_reply_to_user_id": null, "in_reply_to_user_id_str": null, "in_reply_to_screen_name": null, "user": {"id": 2429249618, "id_str": "2429249618", "name": "こはく総書記", "screen_name": "589pr", "location": "銀座で握手", "description": "生年不詳。テネシー州ジャクソン出身。小説家、連勤術師。コロナ禍に揺れる令和初頭の日本を風刺した二部作「Goodwill, いい感じ」「Good bey, Evangelion」で講談社メフィスト賞を受賞。後年は連勤術に没頭し、「40連勤による人体錬成術」と題した論文を発表。経団連から注目を浴びる。", "url": "https://t.co/dFT4P2Uhf2", "entities": {"url": {"urls": [{"url": "https://t.co/dFT4P2Uhf2", "expanded_url": "https://linktr.ee/589pr", "display_url": "linktr.ee/589pr", "indices": [0, 23]}]}, "description": {"urls": []}}, "protected": false, "followers_count": 25904, "friends_count": 371, "listed_count": 138, "created_at": "Sat Apr 05 17:48:55 +0000 2014", "favourites_count": 115809, "utc_offset": null, "time_zone": null, "geo_enabled": false, "verified": false, "statuses_count": 2863, "lang": null, "contributors_enabled": false, "is_translator": false, "is_translation_enabled": false, "profile_background_color": "022330", "profile_background_image_url": "http://abs.twimg.com/images/themes/theme14/bg.gif", "profile_background_image_url_https": "https://abs.twimg.com/images/themes/theme14/bg.gif", "profile_background_tile": true, "profile_image_url": "http://pbs.twimg.com/profile_images/1388337569360793601/DFxlOEhu_normal.jpg", "profile_image_url_https": "https://pbs.twimg.com/profile_images/1388337569360793601/DFxlOEhu_normal.jpg", "profile_banner_url": "https://pbs.twimg.com/profile_banners/2429249618/1609752962", "profile_link_color": "0084B4", "profile_sidebar_border_color": "000000", "profile_sidebar_fill_color": "000000", "profile_text_color": "000000", "profile_use_background_image": true, "has_extended_profile": true, "default_profile": false, "default_profile_image": false, "following": null, "follow_request_sent": null, "notifications": null, "translator_type": "none", "withheld_in_countries": []}, "geo": null, "coordinates": null, "place": null, "contributors": null, "is_quote_status": false, "retweet_count": 0, "favorite_count": 95, "favorited": false, "retweeted": false, "lang": "ja"}, {"created_at": "Tue Dec 14 15:48:55 +0000 2021", "id": 1470782864921088000, "id_str": "1470782864921088000", "full_text": "精神を加速させろ", "truncated": false, "display_text_range": [0, 8], "entities": {"hashtags": [], "symbols": [], "user_mentions": [], "urls": []}, "source": "<a href=\"http://twitter.com/download/iphone\" rel=\"nofollow\">Twitter for iPhone</a>", "in_reply_to_status_id": null, "in_reply_to_status_id_str": null, "in_reply_to_user_id": null, "in_reply_to_user_id_str": null, "in_reply_to_screen_name": null, "user": {"id": 2429249618, "id_str": "2429249618", "name": "こはく総書記", "screen_name": "589pr", "location": "銀座で握手", "description": "生年不詳。テネシー州ジャクソン出身。小説家、連勤術師。コロナ禍に揺れる令和初頭の日本を風刺した二部作「Goodwill, いい感じ」「Good bey, Evangelion」で講談社メフィスト賞を受賞。後年は連勤術に没頭し、「40連勤による人体錬成術」と題した論文を発表。経団連から注目を浴びる。", "url": "https://t.co/dFT4P2Uhf2", "entities": {"url": {"urls": [{"url": "https://t.co/dFT4P2Uhf2", "expanded_url": "https://linktr.ee/589pr", "display_url": "linktr.ee/589pr", "indices": [0, 23]}]}, "description": {"urls": []}}, "protected": false, "followers_count": 25904, "friends_count": 371, "listed_count": 138, "created_at": "Sat Apr 05 17:48:55 +0000 2014", "favourites_count": 115809, "utc_offset": null, "time_zone": null, "geo_enabled": false, "verified": false, "statuses_count": 2863, "lang": null, "contributors_enabled": false, "is_translator": false, "is_translation_enabled": false, "profile_background_color": "022330", "profile_background_image_url": "http://abs.twimg.com/images/themes/theme14/bg.gif", "profile_background_image_url_https": "https://abs.twimg.com/images/themes/theme14/bg.gif", "profile_background_tile": true, "profile_image_url": "http://pbs.twimg.com/profile_images/1388337569360793601/DFxlOEhu_normal.jpg", "profile_image_url_https": "https://pbs.twimg.com/profile_images/1388337569360793601/DFxlOEhu_normal.jpg", "profile_banner_url": "https://pbs.twimg.com/profile_banners/2429249618/1609752962", "profile_link_color": "0084B4", "profile_sidebar_border_color": "000000", "profile_sidebar_fill_color": "000000", "profile_text_color": "000000", "profile_use_background_image": true, "has_extended_profile": true, "default_profile": false, "default_profile_image": false, "following": null, "follow_request_sent": null, "notifications": null, "translator_type": "none", "withheld_in_countries": []}, "geo": null, "coordinates": null, "place": null, "contributors": null, "is_quote_status": false, "retweet_count": 2, "favorite_count": 52, "favorited": false, "retweeted": false, "lang": "ja"}, {"created_at": "Tue Dec 14 03:36:36 +0000 2021", "id": 1470598571187929098, "id_str": "1470598571187929098", "full_text": "そりゃあ、どんぶり勘定ドリブンよ。\n#querie_me \nhttps://t.co/kjsq37sCJf", "truncated": false, "display_text_range": [0, 53], "entities": {"hashtags": [{"text": "querie_me", "indices": [18, 28]}], "symbols": [], "user_mentions": [], "urls": [{"url": "https://t.co/kjsq37sCJf", "expanded_url": "https://querie.me/answer/mGyMfRXEdBLvnhGZCFEC?timestamp=1639452988", "display_url": "querie.me/answer/mGyMfRX…", "indices": [30, 53]}]}, "source": "<a href=\"https://twitter.com/querie_me_app\" rel=\"nofollow\">querie.me</a>", "in_reply_to_status_id": null, "in_reply_to_status_id_str": null, "in_reply_to_user_id": null, "in_reply_to_user_id_str": null, "in_reply_to_screen_name": null, "user": {"id": 2429249618, "id_str": "2429249618", "name": "こはく総書記", "screen_name": "589pr", "location": "銀座で握手", "description": "生年不詳。テネシー州ジャクソン出身。小説家、連勤術師。コロナ禍に揺れる令和初頭の日本を風刺した二部作「Goodwill, いい感じ」「Good bey, Evangelion」で講談社メフィスト賞を受賞。後年は連勤術に没頭し、「40連勤による人体錬成術」と題した論文を発表。経団連から注目を浴びる。", "url": "https://t.co/dFT4P2Uhf2", "entities": {"url": {"urls": [{"url": "https://t.co/dFT4P2Uhf2", "expanded_url": "https://linktr.ee/589pr", "display_url": "linktr.ee/589pr", "indices": [0, 23]}]}, "description": {"urls": []}}, "protected": false, "followers_count": 25904, "friends_count": 371, "listed_count": 138, "created_at": "Sat Apr 05 17:48:55 +0000 2014", "favourites_count": 115809, "utc_offset": null, "time_zone": null, "geo_enabled": false, "verified": false, "statuses_count": 2863, "lang": null, "contributors_enabled": false, "is_translator": false, "is_translation_enabled": false, "profile_background_color": "022330", "profile_background_image_url": "http://abs.twimg.com/images/themes/theme14/bg.gif", "profile_background_image_url_https": "https://abs.twimg.com/images/themes/theme14/bg.gif", "profile_background_tile": true, "profile_image_url": "http://pbs.twimg.com/profile_images/1388337569360793601/DFxlOEhu_normal.jpg", "profile_image_url_https": "https://pbs.twimg.com/profile_images/1388337569360793601/DFxlOEhu_normal.jpg", "profile_banner_url": "https://pbs.twimg.com/profile_banners/2429249618/1609752962", "profile_link_color": "0084B4", "profile_sidebar_border_color": "000000", "profile_sidebar_fill_color": "000000", "profile_text_color": "000000", "profile_use_background_image": true, "has_extended_profile": true, "default_profile": false, "default_profile_image": false, "following": null, "follow_request_sent": null, "notifications": null, "translator_type": "none", "withheld_in_countries": []}, "geo": null, "coordinates": null, "place": null, "contributors": null, "is_quote_status": false, "retweet_count": 0, "favorite_count": 23, "favorited": false, "retweeted": false, "possibly_sensitive": false, "lang": "ja"}, {"created_at": "Tue Dec 14 03:24:36 +0000 2021", "id": 1470595549951033344, "id_str": "1470595549951033344", "full_text": "ダイナミック絶対に新聞を読ませないマン https://t.co/vjw3LFJnkz", "truncated": false, "display_text_range": [0, 19], "entities": {"hashtags": [], "symbols": [], "user_mentions": [], "urls": [], "media": [{"id": 1470595545534058499, "id_str": "1470595545534058499", "indices": [20, 43], "media_url": "http://pbs.twimg.com/media/FGia22vUUAMZRIv.jpg", "media_url_https": "https://pbs.twimg.com/media/FGia22vUUAMZRIv.jpg", "url": "https://t.co/vjw3LFJnkz", "display_url": "pic.twitter.com/vjw3LFJnkz", "expanded_url": "https://twitter.com/589pr/status/1470595549951033344/photo/1", "type": "photo", "sizes": {"thumb": {"w": 150, "h": 150, "resize": "crop"}, "large": {"w": 1478, "h": 1108, "resize": "fit"}, "medium": {"w": 1200, "h": 900, "resize": "fit"}, "small": {"w": 680, "h": 510, "resize": "fit"}}}]}, "extended_entities": {"media": [{"id": 1470595545534058499, "id_str": "1470595545534058499", "indices": [20, 43], "media_url": "http://pbs.twimg.com/media/FGia22vUUAMZRIv.jpg", "media_url_https": "https://pbs.twimg.com/media/FGia22vUUAMZRIv.jpg", "url": "https://t.co/vjw3LFJnkz", "display_url": "pic.twitter.com/vjw3LFJnkz", "expanded_url": "https://twitter.com/589pr/status/1470595549951033344/photo/1", "type": "photo", "sizes": {"thumb": {"w": 150, "h": 150, "resize": "crop"}, "large": {"w": 1478, "h": 1108, "resize": "fit"}, "medium": {"w": 1200, "h": 900, "resize": "fit"}, "small": {"w": 680, "h": 510, "resize": "fit"}}}, {"id": 1470595545538334723, "id_str": "1470595545538334723", "indices": [20, 43], "media_url": "http://pbs.twimg.com/media/FGia22wVkAMqRIQ.jpg", "media_url_https": "https://pbs.twimg.com/media/FGia22wVkAMqRIQ.jpg", "url": "https://t.co/vjw3LFJnkz", "display_url": "pic.twitter.com/vjw3LFJnkz", "expanded_url": "https://twitter.com/589pr/status/1470595549951033344/photo/1", "type": "photo", "sizes": {"thumb": {"w": 150, "h": 150, "resize": "crop"}, "large": {"w": 1478, "h": 1108, "resize": "fit"}, "medium": {"w": 1200, "h": 900, "resize": "fit"}, "small": {"w": 680, "h": 510, "resize": "fit"}}}, {"id": 1470595545534124036, "id_str": "1470595545534124036", "indices": [20, 43], "media_url": "http://pbs.twimg.com/media/FGia22vVUAQBr8_.jpg", "media_url_https": "https://pbs.twimg.com/media/FGia22vVUAQBr8_.jpg", "url": "https://t.co/vjw3LFJnkz", "display_url": "pic.twitter.com/vjw3LFJnkz", "expanded_url": "https://twitter.com/589pr/status/1470595549951033344/photo/1", "type": "photo", "sizes": {"large": {"w": 1513, "h": 960, "resize": "fit"}, "thumb": {"w": 150, "h": 150, "resize": "crop"}, "small": {"w": 680, "h": 431, "resize": "fit"}, "medium": {"w": 1200, "h": 761, "resize": "fit"}}}]}, "source": "<a href=\"http://twitter.com/download/iphone\" rel=\"nofollow\">Twitter for iPhone</a>", "in_reply_to_status_id": null, "in_reply_to_status_id_str": null, "in_reply_to_user_id": null, "in_reply_to_user_id_str": null, "in_reply_to_screen_name": null, "user": {"id": 2429249618, "id_str": "2429249618", "name": "こはく総書記", "screen_name": "589pr", "location": "銀座で握手", "description": "生年不詳。テネシー州ジャクソン出身。小説家、連勤術師。コロナ禍に揺れる令和初頭の日本を風刺した二部作「Goodwill, いい感じ」「Good bey, Evangelion」で講談社メフィスト賞を受賞。後年は連勤術に没頭し、「40連勤による人体錬成術」と題した論文を発表。経団連から注目を浴びる。", "url": "https://t.co/dFT4P2Uhf2", "entities": {"url": {"urls": [{"url": "https://t.co/dFT4P2Uhf2", "expanded_url": "https://linktr.ee/589pr", "display_url": "linktr.ee/589pr", "indices": [0, 23]}]}, "description": {"urls": []}}, "protected": false, "followers_count": 25904, "friends_count": 371, "listed_count": 138, "created_at": "Sat Apr 05 17:48:55 +0000 2014", "favourites_count": 115809, "utc_offset": null, "time_zone": null, "geo_enabled": false, "verified": false, "statuses_count": 2863, "lang": null, "contributors_enabled": false, "is_translator": false, "is_translation_enabled": false, "profile_background_color": "022330", "profile_background_image_url": "http://abs.twimg.com/images/themes/theme14/bg.gif", "profile_background_image_url_https": "https://abs.twimg.com/images/themes/theme14/bg.gif", "profile_background_tile": true, "profile_image_url": "http://pbs.twimg.com/profile_images/1388337569360793601/DFxlOEhu_normal.jpg", "profile_image_url_https": "https://pbs.twimg.com/profile_images/1388337569360793601/DFxlOEhu_normal.jpg", "profile_banner_url": "https://pbs.twimg.com/profile_banners/2429249618/1609752962", "profile_link_color": "0084B4", "profile_sidebar_border_color": "000000", "profile_sidebar_fill_color": "000000", "profile_text_color": "000000", "profile_use_background_image": true, "has_extended_profile": true, "default_profile": false, "default_profile_image": false, "following": null, "follow_request_sent": null, "notifications": null, "translator_type": "none", "withheld_in_countries": []}, "geo": null, "coordinates": null, "place": null, "contributors": null, "is_quote_status": false, "retweet_count": 9, "favorite_count": 163, "favorited": false, "retweeted": false, "possibly_sensitive": false, "lang": "ja"}, {"created_at": "Tue Dec 14 01:20:44 +0000 2021", "id": 1470564378064060418, "id_str": "1470564378064060418", "full_text": "何がいけないのか分からんけど、今日は顔面の宝塚指数すごい。歩くだけで薔薇が咲き乱れる。", "truncated": false, "display_text_range": [0, 43], "entities": {"hashtags": [], "symbols": [], "user_mentions": [], "urls": []}, "source": "<a href=\"http://twitter.com/download/iphone\" rel=\"nofollow\">Twitter for iPhone</a>", "in_reply_to_status_id": null, "in_reply_to_status_id_str": null, "in_reply_to_user_id": null, "in_reply_to_user_id_str": null, "in_reply_to_screen_name": null, "user": {"id": 2429249618, "id_str": "2429249618", "name": "こはく総書記", "screen_name": "589pr", "location": "銀座で握手", "description": "生年不詳。テネシー州ジャクソン出身。小説家、連勤術師。コロナ禍に揺れる令和初頭の日本を風刺した二部作「Goodwill, いい感じ」「Good bey, Evangelion」で講談社メフィスト賞を受賞。後年は連勤術に没頭し、「40連勤による人体錬成術」と題した論文を発表。経団連から注目を浴びる。", "url": "https://t.co/dFT4P2Uhf2", "entities": {"url": {"urls": [{"url": "https://t.co/dFT4P2Uhf2", "expanded_url": "https://linktr.ee/589pr", "display_url": "linktr.ee/589pr", "indices": [0, 23]}]}, "description": {"urls": []}}, "protected": false, "followers_count": 25904, "friends_count": 371, "listed_count": 138, "created_at": "Sat Apr 05 17:48:55 +0000 2014", "favourites_count": 115809, "utc_offset": null, "time_zone": null, "geo_enabled": false, "verified": false, "statuses_count": 2863, "lang": null, "contributors_enabled": false, "is_translator": false, "is_translation_enabled": false, "profile_background_color": "022330", "profile_background_image_url": "http://abs.twimg.com/images/themes/theme14/bg.gif", "profile_background_image_url_https": "https://abs.twimg.com/images/themes/theme14/bg.gif", "profile_background_tile": true, "profile_image_url": "http://pbs.twimg.com/profile_images/1388337569360793601/DFxlOEhu_normal.jpg", "profile_image_url_https": "https://pbs.twimg.com/profile_images/1388337569360793601/DFxlOEhu_normal.jpg", "profile_banner_url": "https://pbs.twimg.com/profile_banners/2429249618/1609752962", "profile_link_color": "0084B4", "profile_sidebar_border_color": "000000", "profile_sidebar_fill_color": "000000", "profile_text_color": "000000", "profile_use_background_image": true, "has_extended_profile": true, "default_profile": false, "default_profile_image": false, "following": null, "follow_request_sent": null, "notifications": null, "translator_type": "none", "withheld_in_countries": []}, "geo": null, "coordinates": null, "place": null, "contributors": null, "is_quote_status": false, "retweet_count": 4, "favorite_count": 381, "favorited": false, "retweeted": false, "lang": "ja"}, {"created_at": "Mon Dec 13 11:35:04 +0000 2021", "id": 1470356593133109248, "id_str": "1470356593133109248", "full_text": "デスクライトに悩んてる人、ScreenBarとにかくおすすめです。", "truncated": false, "display_text_range": [0, 33], "entities": {"hashtags": [], "symbols": [], "user_mentions": [], "urls": []}, "source": "<a href=\"http://twitter.com/download/iphone\" rel=\"nofollow\">Twitter for iPhone</a>", "in_reply_to_status_id": null, "in_reply_to_status_id_str": null, "in_reply_to_user_id": null, "in_reply_to_user_id_str": null, "in_reply_to_screen_name": null, "user": {"id": 2429249618, "id_str": "2429249618", "name": "こはく総書記", "screen_name": "589pr", "location": "銀座で握手", "description": "生年不詳。テネシー州ジャクソン出身。小説家、連勤術師。コロナ禍に揺れる令和初頭の日本を風刺した二部作「Goodwill, いい感じ」「Good bey, Evangelion」で講談社メフィスト賞を受賞。後年は連勤術に没頭し、「40連勤による人体錬成術」と題した論文を発表。経団連から注目を浴びる。", "url": "https://t.co/dFT4P2Uhf2", "entities": {"url": {"urls": [{"url": "https://t.co/dFT4P2Uhf2", "expanded_url": "https://linktr.ee/589pr", "display_url": "linktr.ee/589pr", "indices": [0, 23]}]}, "description": {"urls": []}}, "protected": false, "followers_count": 25904, "friends_count": 371, "listed_count": 138, "created_at": "Sat Apr 05 17:48:55 +0000 2014", "favourites_count": 115809, "utc_offset": null, "time_zone": null, "geo_enabled": false, "verified": false, "statuses_count": 2863, "lang": null, "contributors_enabled": false, "is_translator": false, "is_translation_enabled": false, "profile_background_color": "022330", "profile_background_image_url": "http://abs.twimg.com/images/themes/theme14/bg.gif", "profile_background_image_url_https": "https://abs.twimg.com/images/themes/theme14/bg.gif", "profile_background_tile": true, "profile_image_url": "http://pbs.twimg.com/profile_images/1388337569360793601/DFxlOEhu_normal.jpg", "profile_image_url_https": "https://pbs.twimg.com/profile_images/1388337569360793601/DFxlOEhu_normal.jpg", "profile_banner_url": "https://pbs.twimg.com/profile_banners/2429249618/1609752962", "profile_link_color": "0084B4", "profile_sidebar_border_color": "000000", "profile_sidebar_fill_color": "000000", "profile_text_color": "000000", "profile_use_background_image": true, "has_extended_profile": true, "default_profile": false, "default_profile_image": false, "following": null, "follow_request_sent": null, "notifications": null, "translator_type": "none", "withheld_in_countries": []}, "geo": null, "coordinates": null, "place": null, "contributors": null, "is_quote_status": false, "retweet_count": 5, "favorite_count": 59, "favorited": false, "retweeted": false, "lang": "ja"}, {"created_at": "Mon Dec 13 11:33:58 +0000 2021", "id": 1470356317969973253, "id_str": "1470356317969973253", "full_text": "RT @BenQlighting_jp: \\ScreenBar Halo発売開始/\n\n皆様お待たせいたしました\nScreenBar Haloが12時より発売開始されました🎉\n\nご購入はこちらから⬇️\nhttps://t.co/5xFo1PwC3a\n\n今年最後に史上最高のモニター…", "truncated": false, "display_text_range": [0, 140], "entities": {"hashtags": [], "symbols": [], "user_mentions": [{"screen_name": "BenQlighting_jp", "name": "BenQライティング（照明機器全般）JP💡", "id": 1126746949133037571, "id_str": "1126746949133037571", "indices": [3, 19]}], "urls": [{"url": "https://t.co/5xFo1PwC3a", "expanded_url": "https://item.rakuten.co.jp/benq-directshop/lighting-screenbar-halo/", "display_url": "item.rakuten.co.jp/benq-directsho…", "indices": [100, 123]}]}, "source": "<a href=\"http://twitter.com/download/iphone\" rel=\"nofollow\">Twitter for iPhone</a>", "in_reply_to_status_id": null, "in_reply_to_status_id_str": null, "in_reply_to_user_id": null, "in_reply_to_user_id_str": null, "in_reply_to_screen_name": null, "user": {"id": 2429249618, "id_str": "2429249618", "name": "こはく総書記", "screen_name": "589pr", "location": "銀座で握手", "description": "生年不詳。テネシー州ジャクソン出身。小説家、連勤術師。コロナ禍に揺れる令和初頭の日本を風刺した二部作「Goodwill, いい感じ」「Good bey, Evangelion」で講談社メフィスト賞を受賞。後年は連勤術に没頭し、「40連勤による人体錬成術」と題した論文を発表。経団連から注目を浴びる。", "url": "https://t.co/dFT4P2Uhf2", "entities": {"url": {"urls": [{"url": "https://t.co/dFT4P2Uhf2", "expanded_url": "https://linktr.ee/589pr", "display_url": "linktr.ee/589pr", "indices": [0, 23]}]}, "description": {"urls": []}}, "protected": false, "followers_count": 25904, "friends_count": 371, "listed_count": 138, "created_at": "Sat Apr 05 17:48:55 +0000 2014", "favourites_count": 115809, "utc_offset": null, "time_zone": null, "geo_enabled": false, "verified": false, "statuses_count": 2863, "lang": null, "contributors_enabled": false, "is_translator": false, "is_translation_enabled": false, "profile_background_color": "022330", "profile_background_image_url": "http://abs.twimg.com/images/themes/theme14/bg.gif", "profile_background_image_url_https": "https://abs.twimg.com/images/themes/theme14/bg.gif", "profile_background_tile": true, "profile_image_url": "http://pbs.twimg.com/profile_images/1388337569360793601/DFxlOEhu_normal.jpg", "profile_image_url_https": "https://pbs.twimg.com/profile_images/1388337569360793601/DFxlOEhu_normal.jpg", "profile_banner_url": "https://pbs.twimg.com/profile_banners/2429249618/1609752962", "profile_link_color": "0084B4", "profile_sidebar_border_color": "000000", "profile_sidebar_fill_color": "000000", "profile_text_color": "000000", "profile_use_background_image": true, "has_extended_profile": true, "default_profile": false, "default_profile_image": false, "following": null, "follow_request_sent": null, "notifications": null, "translator_type": "none", "withheld_in_countries": []}, "geo": null, "coordinates": null, "place": null, "contributors": null, "retweeted_status": {"created_at": "Mon Dec 13 03:13:25 +0000 2021", "id": 1470230348995129346, "id_str": "1470230348995129346", "full_text": "\\ScreenBar Halo発売開始/\n\n皆様お待たせいたしました\nScreenBar Haloが12時より発売開始されました🎉\n\nご購入はこちらから⬇️\nhttps://t.co/5xFo1PwC3a\n\n今年最後に史上最高のモニターライトを是非ご堪能ください。\n\n#ScreenBarHalo \n#さらばケーブル https://t.co/TfNnoMGfWv", "truncated": false, "display_text_range": [0, 158], "entities": {"hashtags": [{"text": "ScreenBarHalo", "indices": [134, 148]}, {"text": "さらばケーブル", "indices": [150, 158]}], "symbols": [], "user_mentions": [], "urls": [{"url": "https://t.co/5xFo1PwC3a", "expanded_url": "https://item.rakuten.co.jp/benq-directshop/lighting-screenbar-halo/", "display_url": "item.rakuten.co.jp/benq-directsho…", "indices": [79, 102]}], "media": [{"id": 1470230291897745408, "id_str": "1470230291897745408", "indices": [159, 182], "media_url": "http://pbs.twimg.com/media/FGdOqS6VgAADIBL.jpg", "media_url_https": "https://pbs.twimg.com/media/FGdOqS6VgAADIBL.jpg", "url": "https://t.co/TfNnoMGfWv", "display_url": "pic.twitter.com/TfNnoMGfWv", "expanded_url": "https://twitter.com/BenQlighting_jp/status/1470230348995129346/photo/1", "type": "photo", "sizes": {"thumb": {"w": 150, "h": 150, "resize": "crop"}, "large": {"w": 970, "h": 600, "resize": "fit"}, "small": {"w": 680, "h": 421, "resize": "fit"}, "medium": {"w": 970, "h": 600, "resize": "fit"}}}]}, "extended_entities": {"media": [{"id": 1470230291897745408, "id_str": "1470230291897745408", "indices": [159, 182], "media_url": "http://pbs.twimg.com/media/FGdOqS6VgAADIBL.jpg", "media_url_https": "https://pbs.twimg.com/media/FGdOqS6VgAADIBL.jpg", "url": "https://t.co/TfNnoMGfWv", "display_url": "pic.twitter.com/TfNnoMGfWv", "expanded_url": "https://twitter.com/BenQlighting_jp/status/1470230348995129346/photo/1", "type": "photo", "sizes": {"thumb": {"w": 150, "h": 150, "resize": "crop"}, "large": {"w": 970, "h": 600, "resize": "fit"}, "small": {"w": 680, "h": 421, "resize": "fit"}, "medium": {"w": 970, "h": 600, "resize": "fit"}}}]}, "source": "<a href=\"https://mobile.twitter.com\" rel=\"nofollow\">Twitter Web App</a>", "in_reply_to_status_id": null, "in_reply_to_status_id_str": null, "in_reply_to_user_id": null, "in_reply_to_user_id_str": null, "in_reply_to_screen_name": null, "user": {"id": 1126746949133037571, "id_str": "1126746949133037571", "name": "BenQライティング（照明機器全般）JP💡", "screen_name": "BenQlighting_jp", "location": "モニターの上とか", "description": "台湾の電気製品メーカーBenQ（ベンキュー）の照明機器公式アカウントです。 \n日本のみなさまに生活の中の大事な光を届けるために台湾本社から発信中✨ \n※BenQ Japanとは異なる(ややこしくてすみません)のでお問い合わせはこちらまで→digimarket.jp@BenQ.com", "url": "https://t.co/OBGXbsYrKC", "entities": {"url": {"urls": [{"url": "https://t.co/OBGXbsYrKC", "expanded_url": "https://item.rakuten.co.jp/benq-directshop/c/0000000101/", "display_url": "item.rakuten.co.jp/benq-directsho…", "indices": [0, 23]}]}, "description": {"urls": []}}, "protected": false, "followers_count": 2940, "friends_count": 1073, "listed_count": 24, "created_at": "Fri May 10 07:13:01 +0000 2019", "favourites_count": 5353, "utc_offset": null, "time_zone": null, "geo_enabled": true, "verified": false, "statuses_count": 1524, "lang": null, "contributors_enabled": false, "is_translator": false, "is_translation_enabled": false, "profile_background_color": "000000", "profile_background_image_url": "http://abs.twimg.com/images/themes/theme1/bg.png", "profile_background_image_url_https": "https://abs.twimg.com/images/themes/theme1/bg.png", "profile_background_tile": false, "profile_image_url": "http://pbs.twimg.com/profile_images/1423471346546212864/W4tBC73J_normal.jpg", "profile_image_url_https": "https://pbs.twimg.com/profile_images/1423471346546212864/W4tBC73J_normal.jpg", "profile_banner_url": "https://pbs.twimg.com/profile_banners/1126746949133037571/1639102528", "profile_link_color": "981CEB", "profile_sidebar_border_color": "000000", "profile_sidebar_fill_color": "000000", "profile_text_color": "000000", "profile_use_background_image": false, "has_extended_profile": false, "default_profile": false, "default_profile_image": false, "following": null, "follow_request_sent": null, "notifications": null, "translator_type": "none", "withheld_in_countries": []}, "geo": null, "coordinates": null, "place": null, "contributors": null, "is_quote_status": false, "retweet_count": 33, "favorite_count": 115, "favorited": false, "retweeted": false, "possibly_sensitive": false, "lang": "ja"}, "is_quote_status": false, "retweet_count": 33, "favorite_count": 0, "favorited": false, "retweeted": false, "possibly_sensitive": false, "lang": "ja"}]